luxtools/__init__.py
luxtools/py.typed
luxtools/functional/__init__.py
luxtools/functional/compose.py
luxtools/functional/overload.py
luxtools/functional/partial.py
luxtools/scientific/__init__.py
luxtools/scientific/error_propagation.py
luxtools/scientific/printing.py
luxtools-0.1.1.dist-info/METADATA
luxtools-0.1.1.dist-info/WHEEL
luxtools-0.1.1.dist-info/RECORD
