Metadata-Version: 2.4
Name: luxtools
Version: 0.1.1
Summary: A collection of tools and utilities that I use in my work.
Author-email: lux <luna@lunalux.io>
Requires-Python: >=3.13
Requires-Dist: trycast>=1.2.0
